<?xml version="1.0"?>
<root>
  <OBJECT NAME="MOVIMENTACAO">
    <METHOD NAME="movimentacao_executa_antes_nf" DESCRIPTION="" VERSION="19" TRIGGEROF="MOVIMENTACAO.EV_MOVIMENTACAO_EXECUTA_ANTES_NF" TRIGGERTYPE="0" THREADSAFE="0">
      <PARAMS>
        <GROUPS>
          <GROUP/>
        </GROUPS>
        <PARAM NAME="COD_OPERACAO" FORMAT="N" SIZE="8" PROJECTION="0" FIELDLABEL="Cod Operacao" CTAB="0"/>
        <PARAM NAME="TIPO_OPERACAO" SIZE="1" PROJECTION="0" FIELDLABEL="Tipo Operacao" CTAB="0"/>
        <PARAM NAME="VOID2" FORMAT="N" SIZE="8" PROJECTION="0" FIELDLABEL="Void" CTAB="0"/>
      </PARAMS>
      <FIELDS/>
      <ACTIONSCRIPT>SELECT:CLI
  C.CONTRIBUINTE_ICMS
FROM MOVIMENTO M
  INNER JOIN NF ON NF.COD_OPERACAO=M.COD_OPERACAO AND NF.TIPO_OPERACAO=M.TIPO_OPERACAO
  INNER JOIN CLIENTES C ON C.CLIENTE=M.CLIENTE
WHERE M.COD_OPERACAO =:COD_OPERACAO
AND M.TIPO_OPERACAO =:TIPO_OPERACAO
AND NF.DIGITADA='F'
AND C.PF_PJ='PJ'
AND M.EVENTO='20106'
AND C.CLIENTE NOT IN (SELECT C2.CLIENTE FROM pmz_clientes_emissao_nfe_dev C2 WHERE C2.PERMITIR&lt;>'T');


#SELECT(CLI._EOF,TRUE:{#CHECK("SELECT 1 AS N FROM DUAL",N>0,"Cliente Pessoa Juridica, Necessario emiss&#227;o da Nota de Devolucao pelo cliente!")},ELSE:{});




</ACTIONSCRIPT>
    </METHOD>
  </OBJECT>
</root>